[
    {
        "key": "B002FL8IYK",
        "category": "Basic",
        "location": "Miles",
        "duration": 12,
        "students": 155000,
        "img": "./basic.PNG",
        "star": 4.6,
        "cost": 6641
    },
    {
        "key": "B002HL8IYK",
        "category": "Medium",
        "location": "Sironamhin",
        "duration": 7,
        "students": 160000,
        "img": "./medium.PNG",
        "star": 4.5,
        "cost": 8423
    },
    {
        "key": "B002IL8IYK",
        "category": "Advanced",
        "location": "Sohojia",
        "duration": 3,
        "students": 130000,
        "img": "./advanced.PNG",
        "star": 4.3,
        "cost": 4342
    },
    {
        "key": "B002JL8IYK",
        "category": "Premium",
        "location": "Souls",
        "duration": 13,
        "students": 120000,
        "img": "./premium.PNG",
        "star": 4.1,
        "cost": 3322
    },
    {
        "key": "B002KL8IYK",
        "category": "Proffesional",
        "location": "Warfez",
        "duration": 11,
        "students": 200000,
        "img": "./professional.PNG",
        "star": 4.9,
        "cost": 9991
    },
    {
        "key": "B002RL8IYK",
        "category": "A1",
        "location": "Arbovirus",
        "duration": 6,
        "students": 120000,
        "img": "./A1.PNG",
        "star": 4.3,
        "cost": 3245
    },
    {
        "key": "B002AL8IYK",
        "category": "A2",
        "location": "Artcell",
        "duration": 7,
        "students": 160000,
        "img": "./A2.PNG",
        "star": 4.6,
        "cost": 7745
    },
    {
        "key": "B002BL8IYK",
        "category": "B1",
        "location": "Aurthohin",
        "duration": 8,
        "students": 130000,
        "img": "./B1.PNG",
        "star": 4.4,
        "cost": 5245
    },
    {
        "key": "B002CL8IYK",
        "category": "B2",
        "location": "Black",
        "duration": 4,
        "students": 120000,
        "img": "./B2.PNG",
        "star": 4.1,
        "cost": 2245
    },
    {
        "key": "B002DL8IYK",
        "category": "C1",
        "location": "Chirkut",
        "duration": 7,
        "students": 140000,
        "img": "./C1.PNG",
        "star": 4.8,
        "cost": 8890
    },
    {
        "key": "B002EL8IYK",
        "category": "C2",
        "location": "Meghdol",
        "duration": 4,
        "students": 150000,
        "img": "./C2.PNG",
        "star": 4.6,
        "cost": 6757
    }
]